napari_conference/__init__.py
napari_conference/_widget.py
napari_conference/cli.py
napari_conference/napari.yaml
napari_conference/_tests/__init__.py
napari_conference/_tests/test_widget.py
napari_conference-0.1.0.dist-info/LICENSE
napari_conference-0.1.0.dist-info/METADATA
napari_conference-0.1.0.dist-info/WHEEL
napari_conference-0.1.0.dist-info/entry_points.txt
napari_conference-0.1.0.dist-info/top_level.txt
napari_conference-0.1.0.dist-info/RECORD
