Metadata-Version: 2.1
Name: napari-conference
Version: 0.1.0
Summary: A simple plugin that allows you to use napari + your webcam in video calls
Home-page: https://github.com/kephale/napari-conference
Author: Kyle Harrington
Author-email: czi@kyleharrington.com
License: BSD-3-Clause
Project-URL: Bug Tracker, https://github.com/kephale/napari-conference/issues
Project-URL: Documentation, https://github.com/kephale/napari-conference#README.md
Project-URL: Source Code, https://github.com/kephale/napari-conference
Project-URL: User Support, https://github.com/kephale/napari-conference/issues
Classifier: Development Status :: 2 - Pre-Alpha
Classifier: Framework :: napari
Classifier: Intended Audience :: Developers
Classifier: License :: OSI Approved :: BSD License
Classifier: Operating System :: OS Independent
Classifier: Programming Language :: Python
Classifier: Programming Language :: Python :: 3
Classifier: Programming Language :: Python :: 3 :: Only
Classifier: Programming Language :: Python :: 3.8
Classifier: Programming Language :: Python :: 3.9
Classifier: Programming Language :: Python :: 3.10
Classifier: Topic :: Scientific/Engineering :: Image Processing
Requires-Python: >=3.8
License-File: LICENSE
Requires-Dist: numpy
Requires-Dist: magicgui
Requires-Dist: qtpy
Requires-Dist: opencv-python
Requires-Dist: pyvirtualcam
Provides-Extra: testing
Requires-Dist: tox ; extra == 'testing'
Requires-Dist: pytest ; extra == 'testing'
Requires-Dist: pytest-cov ; extra == 'testing'
Requires-Dist: pytest-qt ; extra == 'testing'
Requires-Dist: napari ; extra == 'testing'
Requires-Dist: pyqt5 ; extra == 'testing'
